pageserver/__init__.py
pageserver/core.py
pageserver/manage.py
pageserver/router.py
pageserver/server.py
pageserver/background/__init__.py
pageserver/cache/__init__.py
pageserver/cache/keys.py
pageserver/cache/backend/__init__.py
pageserver/cache/backend/memory_cache.py
pageserver/cache/backend/redis_cache.py
pageserver/conf/__init__.py
pageserver/conf/default.py
pageserver/db/__init__.py
pageserver/db/fields.py
pageserver/db/format.py
pageserver/db/function.py
pageserver/db/models.py
pageserver/db/query.py
pageserver/db/backend/__init__.py
pageserver/db/backend/utils.py
pageserver/db/backend/mysql/__init__.py
pageserver/db/backend/mysql/helper.py
pageserver/db/backend/mysql/sql.py
pageserver/db/backend/sqlite3/__init__.py
pageserver/db/backend/sqlite3/helper.py
pageserver/db/backend/sqlite3/sql.py
pageserver/http/__init__.py
pageserver/http/exception.py
pageserver/http/multipart_data.py
pageserver/http/query_dict.py
pageserver/http/request.py
pageserver/http/response.py
pageserver/http/status.py
pageserver/http/websocket.py
pageserver/layers/__init__.py
pageserver/layers/backend/__init__.py
pageserver/layers/backend/memory_layer.py
pageserver/layers/backend/redis_layer.py
pageserver/manage/__init__.py
pageserver/manage/migrate.py
pageserver/manage/model.py
pageserver/manage/setup.py
pageserver/sites/__init__.py
pageserver/sites/admin/__init__.py
pageserver/sites/admin/middleware.py
pageserver/sites/admin/model.py
pageserver/sites/admin/secrets.py
pageserver/sites/admin/settings.py
pageserver/sites/admin/urls.py
pageserver/sites/admin/static/app/app.css
pageserver/sites/admin/static/app/app.js
pageserver/sites/admin/static/app/menu.css
pageserver/sites/admin/static/app/account/page.css
pageserver/sites/admin/static/app/account/page.html
pageserver/sites/admin/static/app/account/page.js
pageserver/sites/admin/static/app/account/edit/page.css
pageserver/sites/admin/static/app/account/edit/page.html
pageserver/sites/admin/static/app/account/edit/page.js
pageserver-0.0.2.dist-info/LICENSE
pageserver-0.0.2.dist-info/METADATA
pageserver-0.0.2.dist-info/WHEEL
pageserver-0.0.2.dist-info/top_level.txt
pageserver-0.0.2.dist-info/RECORD
