Metadata-Version: 2.1
Name: pageserver
Version: 0.0.2
Summary: a asyncio web framework.
Author-email: song zirui <pochnsong@163.com>
Project-URL: Homepage, https://github.com/pochnsong/pageserver.git
Project-URL: Documentation, https://github.com/pochnsong/pageserver/wiki
Project-URL: Repository, https://github.com/pochnsong/pageserver.git
Project-URL: Issues, https://github.com/pochnsong/pageserver/issues
Classifier: Programming Language :: Python :: 3
Classifier: License :: OSI Approved :: GNU General Public License v3 (GPLv3)
Classifier: Operating System :: OS Independent
Requires-Python: >=3.11
License-File: LICENSE
